openfeature/.gitignore
openfeature/contrib/provider/flagd/__init__.py
openfeature/contrib/provider/flagd/config.py
openfeature/contrib/provider/flagd/flag_type.py
openfeature/contrib/provider/flagd/provider.py
openfeature/contrib/provider/flagd/sync_metadata_hook.py
openfeature/contrib/provider/flagd/resolvers/__init__.py
openfeature/contrib/provider/flagd/resolvers/grpc.py
openfeature/contrib/provider/flagd/resolvers/in_process.py
openfeature/contrib/provider/flagd/resolvers/protocol.py
openfeature/contrib/provider/flagd/resolvers/process/custom_ops.py
openfeature/contrib/provider/flagd/resolvers/process/flags.py
openfeature/contrib/provider/flagd/resolvers/process/targeting.py
openfeature/contrib/provider/flagd/resolvers/process/connector/__init__.py
openfeature/contrib/provider/flagd/resolvers/process/connector/file_watcher.py
openfeature/contrib/provider/flagd/resolvers/process/connector/grpc_watcher.py
openfeature/schemas/protobuf/flagd/evaluation/v1/evaluation_pb2.py
openfeature/schemas/protobuf/flagd/evaluation/v1/evaluation_pb2.pyi
openfeature/schemas/protobuf/flagd/evaluation/v1/evaluation_pb2_grpc.py
openfeature/schemas/protobuf/flagd/evaluation/v1/evaluation_pb2_grpc.pyi
openfeature/schemas/protobuf/flagd/sync/v1/sync_pb2.py
openfeature/schemas/protobuf/flagd/sync/v1/sync_pb2.pyi
openfeature/schemas/protobuf/flagd/sync/v1/sync_pb2_grpc.py
openfeature/schemas/protobuf/flagd/sync/v1/sync_pb2_grpc.pyi
openfeature/schemas/protobuf/schema/v1/schema_pb2.py
openfeature/schemas/protobuf/schema/v1/schema_pb2.pyi
openfeature/schemas/protobuf/schema/v1/schema_pb2_grpc.py
openfeature/schemas/protobuf/schema/v1/schema_pb2_grpc.pyi
openfeature/schemas/protobuf/sync/v1/sync_service_pb2.py
openfeature/schemas/protobuf/sync/v1/sync_service_pb2.pyi
openfeature/schemas/protobuf/sync/v1/sync_service_pb2_grpc.py
openfeature/schemas/protobuf/sync/v1/sync_service_pb2_grpc.pyi
openfeature_provider_flagd-0.2.6.dist-info/METADATA
openfeature_provider_flagd-0.2.6.dist-info/WHEEL
openfeature_provider_flagd-0.2.6.dist-info/licenses/LICENSE
openfeature_provider_flagd-0.2.6.dist-info/RECORD
