Metadata-Version: 2.4
Name: openfeature-provider-flagd
Version: 0.2.6
Summary: OpenFeature provider for the flagd flag evaluation engine
Project-URL: Homepage, https://github.com/open-feature/python-sdk-contrib
Author-email: OpenFeature <openfeature-core@groups.io>
License:                                  Apache License
License-File: LICENSE
Classifier: License :: OSI Approved :: Apache Software License
Classifier: Programming Language :: Python
Classifier: Programming Language :: Python :: 3
Requires-Python: >=3.9
Requires-Dist: cachebox
Requires-Dist: grpcio>=1.68.1
Requires-Dist: mmh3>=4.1.0
Requires-Dist: openfeature-sdk>=0.6.0
Requires-Dist: panzi-json-logic>=1.0.1
Requires-Dist: protobuf>=5.26.1
Requires-Dist: pyyaml>=6.0.1
Requires-Dist: semver<4,>=3
